AtomisticReverseMonteCarlo/__init__.py
AtomisticReverseMonteCarlo-0.0.3.dist-info/METADATA
AtomisticReverseMonteCarlo-0.0.3.dist-info/WHEEL
AtomisticReverseMonteCarlo-0.0.3.dist-info/entry_points.txt
AtomisticReverseMonteCarlo-0.0.3.dist-info/top_level.txt
AtomisticReverseMonteCarlo-0.0.3.dist-info/RECORD
